odoo/addons/l10n_nl_partner_name/README.rst
odoo/addons/l10n_nl_partner_name/__init__.py
odoo/addons/l10n_nl_partner_name/__manifest__.py
odoo/addons/l10n_nl_partner_name/data/ir.config_parameter.xml
odoo/addons/l10n_nl_partner_name/i18n/l10n_nl_partner_name.pot
odoo/addons/l10n_nl_partner_name/i18n/nl.po
odoo/addons/l10n_nl_partner_name/model/__init__.py
odoo/addons/l10n_nl_partner_name/model/res_partner.py
odoo/addons/l10n_nl_partner_name/scripts/guess_names.py
odoo/addons/l10n_nl_partner_name/static/description/icon.png
odoo/addons/l10n_nl_partner_name/static/src/img/icon.png
odoo/addons/l10n_nl_partner_name/tests/__init__.py
odoo/addons/l10n_nl_partner_name/tests/test_l10n_nl_partner_name.py
odoo/addons/l10n_nl_partner_name/views/res_partner.xml
odoo13_addon_l10n_nl_partner_name-13.0.1.0.1.dev3.dist-info/METADATA
odoo13_addon_l10n_nl_partner_name-13.0.1.0.1.dev3.dist-info/WHEEL
odoo13_addon_l10n_nl_partner_name-13.0.1.0.1.dev3.dist-info/top_level.txt
odoo13_addon_l10n_nl_partner_name-13.0.1.0.1.dev3.dist-info/RECORD
